setup.py
pyter/__init__.py
pyter/ter.py
pyter.egg-info/PKG-INFO
pyter.egg-info/SOURCES.txt
pyter.egg-info/dependency_links.txt
pyter.egg-info/requires.txt
pyter.egg-info/top_level.txt