Metadata-Version: 1.0
Name: pyter
Version: 0.1.1
Summary: Simple ffuzzy matching library using Translation Error Rate algorithm
Home-page: https://github.com/aflc/pyter
Author: Hiroyuki Tanaka
Author-email: aflc0x@gmail.com
License: UNKNOWN
Platform: any
Classifier: Development Status :: 4 - Beta
Classifier: Environment :: Console
Classifier: Intended Audience :: Information Technology
Classifier: Intended Audience :: End Users/Desktop
Classifier: Intended Audience :: Developers
Classifier: Intended Audience :: Science/Research
Classifier: License :: OSI Approved :: MIT License
Classifier: Programming Language :: Python
Classifier: Programming Language :: Python :: 2.6
Classifier: Programming Language :: Python :: 2.7
Classifier: Programming Language :: Python :: 3
Classifier: Topic :: Text Processing
